fastapi_react_toolkit/__init__.py
fastapi_react_toolkit/apis.py
fastapi_react_toolkit/auth.py
fastapi_react_toolkit/const.py
fastapi_react_toolkit/db.py
fastapi_react_toolkit/decorators.py
fastapi_react_toolkit/dependencies.py
fastapi_react_toolkit/filters.py
fastapi_react_toolkit/globals.py
fastapi_react_toolkit/hasher.py
fastapi_react_toolkit/manager.py
fastapi_react_toolkit/model.py
fastapi_react_toolkit/models.py
fastapi_react_toolkit/routers.py
fastapi_react_toolkit/schemas.py
fastapi_react_toolkit/types.py
fastapi_react_toolkit/utils.py
fastapi_react_toolkit/api/__init__.py
fastapi_react_toolkit/api/interface.py
fastapi_react_toolkit/api/utils.py
fastapi_react_toolkit/generic/__init__.py
fastapi_react_toolkit/generic/db.py
fastapi_react_toolkit/generic/filters.py
fastapi_react_toolkit/generic/interface.py
fastapi_react_toolkit/generic/model.py
fastapi_react_toolkit-0.0.0.dist-info/LICENSE
fastapi_react_toolkit-0.0.0.dist-info/METADATA
fastapi_react_toolkit-0.0.0.dist-info/WHEEL
fastapi_react_toolkit-0.0.0.dist-info/top_level.txt
fastapi_react_toolkit-0.0.0.dist-info/RECORD
