Metadata-Version: 2.1
Name: fastapi-react-toolkit
Version: 0.0.0
Summary: A small example package
Author-email: Matthias Leinweber <m.leinweber@datatactics.de>
Project-URL: Homepage, https://github.com/dttctcs/fastapi-react-toolkit
Project-URL: Issues, https://github.com/dttctcs/fastapi-react-toolkit/issues
Classifier: Programming Language :: Python :: 3
Classifier: License :: OSI Approved :: MIT License
Classifier: Operating System :: OS Independent
Requires-Python: >=3.8
License-File: LICENSE
Requires-Dist: fastapi-users[oauth,sqlalchemy]
Requires-Dist: sqlalchemy-utils
